{
  "data": [
    {
      "iteration": 0,
      "energy": -0.02463598794268084,
      "backend": "low_esp"
    },
    {
      "iteration": 1,
      "energy": -0.16613993768947188,
      "backend": "low_esp"
    },
    {
      "iteration": 2,
      "energy": -0.22489472836013116,
      "backend": "low_esp"
    },
    {
      "iteration": 3,
      "energy": -0.22314722809646745,
      "backend": "low_esp"
    },
    {
      "iteration": 4,
      "energy": -0.15592436193703346,
      "backend": "low_esp"
    },
    {
      "iteration": 5,
      "energy": -0.0865850333387987,
      "backend": "low_esp"
    },
    {
      "iteration": 6,
      "energy": -0.1550706995084204,
      "backend": "low_esp"
    },
    {
      "iteration": 7,
      "energy": -0.1774235178854059,
      "backend": "low_esp"
    },
    {
      "iteration": 8,
      "energy": -0.18624043702813564,
      "backend": "low_esp"
    },
    {
      "iteration": 9,
      "energy": -0.19361406293313455,
      "backend": "low_esp"
    },
    {
      "iteration": 10,
      "energy": -0.2512740973143923,
      "backend": "low_esp"
    },
    {
      "iteration": 11,
      "energy": -0.16927496915971665,
      "backend": "low_esp"
    },
    {
      "iteration": 12,
      "energy": -0.2768279067214046,
      "backend": "low_esp"
    },
    {
      "iteration": 13,
      "energy": -0.16620406949605124,
      "backend": "low_esp"
    },
    {
      "iteration": 14,
      "energy": -0.21625010056782867,
      "backend": "low_esp"
    },
    {
      "iteration": 15,
      "energy": -0.27660580445246996,
      "backend": "low_esp"
    },
    {
      "iteration": 16,
      "energy": -0.1707106723305049,
      "backend": "low_esp"
    },
    {
      "iteration": 17,
      "energy": -0.30363804582992177,
      "backend": "low_esp"
    },
    {
      "iteration": 18,
      "energy": -0.20463952661422413,
      "backend": "low_esp"
    },
    {
      "iteration": 19,
      "energy": -0.29883522582339433,
      "backend": "low_esp"
    },
    {
      "iteration": 20,
      "energy": -0.2671569477516363,
      "backend": "low_esp"
    },
    {
      "iteration": 21,
      "energy": -0.29365612584014955,
      "backend": "low_esp"
    },
    {
      "iteration": 22,
      "energy": -0.27082886108346316,
      "backend": "low_esp"
    },
    {
      "iteration": 23,
      "energy": -0.23493062648959445,
      "backend": "low_esp"
    },
    {
      "iteration": 24,
      "energy": -0.32091956049095066,
      "backend": "low_esp"
    },
    {
      "iteration": 25,
      "energy": -0.3625326235347028,
      "backend": "low_esp"
    },
    {
      "iteration": 26,
      "energy": -0.36540951451705256,
      "backend": "low_esp"
    },
    {
      "iteration": 27,
      "energy": -0.32592275851074126,
      "backend": "low_esp"
    },
    {
      "iteration": 28,
      "energy": -0.3667831931184199,
      "backend": "low_esp"
    },
    {
      "iteration": 29,
      "energy": -0.4437196458722229,
      "backend": "low_esp"
    },
    {
      "iteration": 30,
      "energy": -0.40725005208194726,
      "backend": "low_esp"
    },
    {
      "iteration": 31,
      "energy": -0.42477888858727675,
      "backend": "low_esp"
    },
    {
      "iteration": 32,
      "energy": -0.3882850618871237,
      "backend": "low_esp"
    },
    {
      "iteration": 33,
      "energy": -0.43753912292288877,
      "backend": "low_esp"
    },
    {
      "iteration": 34,
      "energy": -0.45761928807513674,
      "backend": "low_esp"
    },
    {
      "iteration": 35,
      "energy": -0.3835537911295481,
      "backend": "low_esp"
    },
    {
      "iteration": 36,
      "energy": -0.4297888248187768,
      "backend": "low_esp"
    },
    {
      "iteration": 37,
      "energy": -0.42079491230415694,
      "backend": "low_esp"
    },
    {
      "iteration": 38,
      "energy": -0.3772439675144466,
      "backend": "low_esp"
    },
    {
      "iteration": 39,
      "energy": -0.48323432664252547,
      "backend": "low_esp"
    },
    {
      "iteration": 40,
      "energy": -0.44234924411861676,
      "backend": "low_esp"
    },
    {
      "iteration": 41,
      "energy": -0.5532856792671672,
      "backend": "low_esp"
    },
    {
      "iteration": 42,
      "energy": -0.563690818896679,
      "backend": "low_esp"
    },
    {
      "iteration": 43,
      "energy": -0.552634845921177,
      "backend": "low_esp"
    },
    {
      "iteration": 44,
      "energy": -0.5675890812214002,
      "backend": "low_esp"
    },
    {
      "iteration": 45,
      "energy": -0.5583252077607639,
      "backend": "low_esp"
    },
    {
      "iteration": 46,
      "energy": -0.5702980097921538,
      "backend": "low_esp"
    },
    {
      "iteration": 47,
      "energy": -0.5525527201693543,
      "backend": "low_esp"
    },
    {
      "iteration": 48,
      "energy": -0.5522024996907245,
      "backend": "low_esp"
    },
    {
      "iteration": 49,
      "energy": -0.5357729173351343,
      "backend": "low_esp"
    },
    {
      "iteration": 50,
      "energy": -0.5338424153786653,
      "backend": "low_esp"
    },
    {
      "iteration": 51,
      "energy": -0.5216423170083089,
      "backend": "low_esp"
    },
    {
      "iteration": 52,
      "energy": -0.5740607697543095,
      "backend": "low_esp"
    },
    {
      "iteration": 53,
      "energy": -0.46233633288863984,
      "backend": "low_esp"
    },
    {
      "iteration": 54,
      "energy": -0.5810066388293564,
      "backend": "low_esp"
    },
    {
      "iteration": 55,
      "energy": -0.5511263980726894,
      "backend": "low_esp"
    },
    {
      "iteration": 56,
      "energy": -0.5681329590377676,
      "backend": "low_esp"
    },
    {
      "iteration": 57,
      "energy": -0.5695656501878115,
      "backend": "low_esp"
    },
    {
      "iteration": 58,
      "energy": -0.5561369219894328,
      "backend": "low_esp"
    },
    {
      "iteration": 59,
      "energy": -0.5858916456361447,
      "backend": "low_esp"
    },
    {
      "iteration": 60,
      "energy": -0.6472102222869477,
      "backend": "low_esp"
    },
    {
      "iteration": 61,
      "energy": -0.4438780146603599,
      "backend": "low_esp"
    },
    {
      "iteration": 62,
      "energy": -0.6024355138740749,
      "backend": "low_esp"
    },
    {
      "iteration": 63,
      "energy": -0.5658245048172823,
      "backend": "low_esp"
    },
    {
      "iteration": 64,
      "energy": -0.6076700984152869,
      "backend": "low_esp"
    },
    {
      "iteration": 65,
      "energy": -0.4954965343294201,
      "backend": "low_esp"
    },
    {
      "iteration": 66,
      "energy": -0.5993519894596049,
      "backend": "low_esp"
    },
    {
      "iteration": 67,
      "energy": -0.47346000052365544,
      "backend": "low_esp"
    },
    {
      "iteration": 68,
      "energy": -0.6650291080941704,
      "backend": "low_esp"
    },
    {
      "iteration": 69,
      "energy": -0.5957997207097291,
      "backend": "low_esp"
    },
    {
      "iteration": 70,
      "energy": -0.6429525786459526,
      "backend": "low_esp"
    },
    {
      "iteration": 71,
      "energy": -0.614909851543649,
      "backend": "low_esp"
    },
    {
      "iteration": 72,
      "energy": -0.6459892300019744,
      "backend": "low_esp"
    },
    {
      "iteration": 73,
      "energy": -0.5463669837801621,
      "backend": "low_esp"
    },
    {
      "iteration": 74,
      "energy": -0.6299812799604956,
      "backend": "low_esp"
    },
    {
      "iteration": 75,
      "energy": -0.6167324634362643,
      "backend": "low_esp"
    },
    {
      "iteration": 76,
      "energy": -0.6396901271102071,
      "backend": "low_esp"
    },
    {
      "iteration": 77,
      "energy": -0.564941452099854,
      "backend": "low_esp"
    },
    {
      "iteration": 78,
      "energy": -0.6160433731792204,
      "backend": "low_esp"
    },
    {
      "iteration": 79,
      "energy": -0.637567236700641,
      "backend": "low_esp"
    },
    {
      "iteration": 80,
      "energy": -0.6511705867015013,
      "backend": "low_esp"
    },
    {
      "iteration": 81,
      "energy": -0.5755202593646479,
      "backend": "low_esp"
    },
    {
      "iteration": 82,
      "energy": -0.6453536025151403,
      "backend": "low_esp"
    },
    {
      "iteration": 83,
      "energy": -0.6113222399110461,
      "backend": "low_esp"
    },
    {
      "iteration": 84,
      "energy": -0.6620906310684568,
      "backend": "low_esp"
    },
    {
      "iteration": 85,
      "energy": -0.6016424958862503,
      "backend": "low_esp"
    },
    {
      "iteration": 86,
      "energy": -0.6609888789383296,
      "backend": "low_esp"
    },
    {
      "iteration": 87,
      "energy": -0.7069915465445111,
      "backend": "low_esp"
    },
    {
      "iteration": 88,
      "energy": -0.6831934836091474,
      "backend": "low_esp"
    },
    {
      "iteration": 89,
      "energy": -0.6877127927192196,
      "backend": "low_esp"
    },
    {
      "iteration": 90,
      "energy": -0.7053503447290768,
      "backend": "low_esp"
    },
    {
      "iteration": 91,
      "energy": -0.6264452194310431,
      "backend": "low_esp"
    },
    {
      "iteration": 92,
      "energy": -0.71170775940985,
      "backend": "low_esp"
    },
    {
      "iteration": 93,
      "energy": -0.6577481623768516,
      "backend": "low_esp"
    },
    {
      "iteration": 94,
      "energy": -0.7263489563166421,
      "backend": "low_esp"
    },
    {
      "iteration": 95,
      "energy": -0.5398924544209575,
      "backend": "low_esp"
    },
    {
      "iteration": 96,
      "energy": -0.7168109720559532,
      "backend": "low_esp"
    },
    {
      "iteration": 97,
      "energy": -0.6934276549336221,
      "backend": "low_esp"
    },
    {
      "iteration": 98,
      "energy": -0.7135643302844781,
      "backend": "low_esp"
    },
    {
      "iteration": 99,
      "energy": -0.7216113169034142,
      "backend": "low_esp"
    },
    {
      "iteration": 100,
      "energy": -0.7099418193430456,
      "backend": "low_esp"
    },
    {
      "iteration": 101,
      "energy": -0.7554215658609494,
      "backend": "low_esp"
    },
    {
      "iteration": 102,
      "energy": -0.7684154806640239,
      "backend": "low_esp"
    },
    {
      "iteration": 103,
      "energy": -0.720046909733585,
      "backend": "low_esp"
    },
    {
      "iteration": 104,
      "energy": -0.7565788198508661,
      "backend": "low_esp"
    },
    {
      "iteration": 105,
      "energy": -0.7621241977578685,
      "backend": "low_esp"
    },
    {
      "iteration": 106,
      "energy": -0.7341160109014285,
      "backend": "low_esp"
    },
    {
      "iteration": 107,
      "energy": -0.7752267397030619,
      "backend": "low_esp"
    },
    {
      "iteration": 108,
      "energy": -0.7264498394178245,
      "backend": "low_esp"
    },
    {
      "iteration": 109,
      "energy": -0.6933540816382244,
      "backend": "low_esp"
    },
    {
      "iteration": 110,
      "energy": -0.7875389874941022,
      "backend": "low_esp"
    },
    {
      "iteration": 111,
      "energy": -0.6906764627611534,
      "backend": "low_esp"
    },
    {
      "iteration": 112,
      "energy": -0.7442523432286645,
      "backend": "low_esp"
    },
    {
      "iteration": 113,
      "energy": -0.6968477795736794,
      "backend": "low_esp"
    },
    {
      "iteration": 114,
      "energy": -0.7724707537213331,
      "backend": "low_esp"
    },
    {
      "iteration": 115,
      "energy": -0.7383053255098162,
      "backend": "low_esp"
    },
    {
      "iteration": 116,
      "energy": -0.7824226435506996,
      "backend": "low_esp"
    },
    {
      "iteration": 117,
      "energy": -0.6837260907950948,
      "backend": "low_esp"
    },
    {
      "iteration": 118,
      "energy": -0.820439769089806,
      "backend": "low_esp"
    },
    {
      "iteration": 119,
      "energy": -0.746013313391205,
      "backend": "low_esp"
    },
    {
      "iteration": 120,
      "energy": -0.8027213872861334,
      "backend": "low_esp"
    },
    {
      "iteration": 121,
      "energy": -0.7287563096974811,
      "backend": "low_esp"
    },
    {
      "iteration": 122,
      "energy": -0.8347226527785762,
      "backend": "low_esp"
    },
    {
      "iteration": 123,
      "energy": -0.5979448194544076,
      "backend": "low_esp"
    },
    {
      "iteration": 124,
      "energy": -0.8288548140143631,
      "backend": "low_esp"
    },
    {
      "iteration": 125,
      "energy": -0.8243554463982464,
      "backend": "low_esp"
    },
    {
      "iteration": 126,
      "energy": -0.8318146494011879,
      "backend": "low_esp"
    },
    {
      "iteration": 127,
      "energy": -0.7566778938821573,
      "backend": "low_esp"
    },
    {
      "iteration": 128,
      "energy": -0.8181224762220919,
      "backend": "low_esp"
    },
    {
      "iteration": 129,
      "energy": -0.7569852909571474,
      "backend": "low_esp"
    },
    {
      "iteration": 130,
      "energy": -0.8091978978349682,
      "backend": "low_esp"
    },
    {
      "iteration": 131,
      "energy": -0.8084460102869566,
      "backend": "low_esp"
    },
    {
      "iteration": 132,
      "energy": -0.8537631019309684,
      "backend": "low_esp"
    },
    {
      "iteration": 133,
      "energy": -0.7890961552973963,
      "backend": "low_esp"
    },
    {
      "iteration": 134,
      "energy": -0.8402895697955656,
      "backend": "low_esp"
    },
    {
      "iteration": 135,
      "energy": -0.7699068778483066,
      "backend": "low_esp"
    },
    {
      "iteration": 136,
      "energy": -0.8225599713352069,
      "backend": "low_esp"
    },
    {
      "iteration": 137,
      "energy": -0.8083107787631094,
      "backend": "low_esp"
    },
    {
      "iteration": 138,
      "energy": -0.8580526806261572,
      "backend": "low_esp"
    },
    {
      "iteration": 139,
      "energy": -0.7329687034121461,
      "backend": "low_esp"
    },
    {
      "iteration": 140,
      "energy": -0.8817737904375734,
      "backend": "low_esp"
    },
    {
      "iteration": 141,
      "energy": -0.8161772650220344,
      "backend": "low_esp"
    },
    {
      "iteration": 142,
      "energy": -0.8743745139061833,
      "backend": "low_esp"
    },
    {
      "iteration": 143,
      "energy": -0.8600835008617859,
      "backend": "low_esp"
    },
    {
      "iteration": 144,
      "energy": -0.8914584722717888,
      "backend": "low_esp"
    },
    {
      "iteration": 145,
      "energy": -0.7527017131760301,
      "backend": "low_esp"
    },
    {
      "iteration": 146,
      "energy": -0.8843215284326454,
      "backend": "low_esp"
    },
    {
      "iteration": 147,
      "energy": -0.9100743367442723,
      "backend": "low_esp"
    },
    {
      "iteration": 148,
      "energy": -0.8920288794238082,
      "backend": "low_esp"
    },
    {
      "iteration": 149,
      "energy": -0.9073365893432712,
      "backend": "low_esp"
    },
    {
      "iteration": 150,
      "energy": -0.9171813549362905,
      "backend": "low_esp"
    },
    {
      "iteration": 151,
      "energy": -0.8777112520562067,
      "backend": "low_esp"
    },
    {
      "iteration": 152,
      "energy": -0.9060394039722552,
      "backend": "low_esp"
    },
    {
      "iteration": 153,
      "energy": -0.7905912460101315,
      "backend": "low_esp"
    },
    {
      "iteration": 154,
      "energy": -0.8932021331229077,
      "backend": "low_esp"
    },
    {
      "iteration": 155,
      "energy": -0.8070051861274887,
      "backend": "low_esp"
    },
    {
      "iteration": 156,
      "energy": -0.8981936002908906,
      "backend": "low_esp"
    },
    {
      "iteration": 157,
      "energy": -0.9046375032796289,
      "backend": "low_esp"
    },
    {
      "iteration": 158,
      "energy": -0.9059433074459284,
      "backend": "low_esp"
    },
    {
      "iteration": 159,
      "energy": -0.800212864660219,
      "backend": "low_esp"
    },
    {
      "iteration": 160,
      "energy": -0.913070254538007,
      "backend": "low_esp"
    },
    {
      "iteration": 161,
      "energy": -0.8842327707845176,
      "backend": "low_esp"
    },
    {
      "iteration": 162,
      "energy": -0.9089956469922706,
      "backend": "low_esp"
    },
    {
      "iteration": 163,
      "energy": -0.9397021441868157,
      "backend": "low_esp"
    },
    {
      "iteration": 164,
      "energy": -0.9180040044480963,
      "backend": "low_esp"
    },
    {
      "iteration": 165,
      "energy": -0.9139955914181218,
      "backend": "low_esp"
    },
    {
      "iteration": 166,
      "energy": -0.8981288288878575,
      "backend": "low_esp"
    },
    {
      "iteration": 167,
      "energy": -0.9188098388144451,
      "backend": "low_esp"
    },
    {
      "iteration": 168,
      "energy": -0.8961003864111647,
      "backend": "low_esp"
    },
    {
      "iteration": 169,
      "energy": -0.9232650558269545,
      "backend": "low_esp"
    },
    {
      "iteration": 170,
      "energy": -0.8824371997038545,
      "backend": "low_esp"
    },
    {
      "iteration": 171,
      "energy": -0.9373792449016867,
      "backend": "low_esp"
    },
    {
      "iteration": 172,
      "energy": -0.9027544441835849,
      "backend": "low_esp"
    },
    {
      "iteration": 173,
      "energy": -0.9030614211545814,
      "backend": "low_esp"
    },
    {
      "iteration": 174,
      "energy": -0.8857273794847589,
      "backend": "low_esp"
    },
    {
      "iteration": 175,
      "energy": -0.926615780121415,
      "backend": "low_esp"
    },
    {
      "iteration": 176,
      "energy": -0.8832138959506513,
      "backend": "low_esp"
    },
    {
      "iteration": 177,
      "energy": -0.9154683136930799,
      "backend": "low_esp"
    },
    {
      "iteration": 178,
      "energy": -0.890137976999269,
      "backend": "low_esp"
    },
    {
      "iteration": 179,
      "energy": -0.8993382843345497,
      "backend": "low_esp"
    },
    {
      "iteration": 180,
      "energy": -0.8993006251304938,
      "backend": "low_esp"
    },
    {
      "iteration": 181,
      "energy": -0.8995620961034553,
      "backend": "low_esp"
    },
    {
      "iteration": 182,
      "energy": -0.9269855176222568,
      "backend": "low_esp"
    },
    {
      "iteration": 183,
      "energy": -0.8948621627057591,
      "backend": "low_esp"
    },
    {
      "iteration": 184,
      "energy": -0.90049495740002,
      "backend": "low_esp"
    },
    {
      "iteration": 185,
      "energy": -0.9106387045130404,
      "backend": "low_esp"
    },
    {
      "iteration": 186,
      "energy": -0.9008210764849113,
      "backend": "low_esp"
    },
    {
      "iteration": 187,
      "energy": -0.9129536259496263,
      "backend": "low_esp"
    },
    {
      "iteration": 188,
      "energy": -0.9544914156509356,
      "backend": "low_esp"
    },
    {
      "iteration": 189,
      "energy": -0.9587641271202576,
      "backend": "low_esp"
    },
    {
      "iteration": 190,
      "energy": -0.9358124570745634,
      "backend": "low_esp"
    },
    {
      "iteration": 191,
      "energy": -0.9449372925382906,
      "backend": "low_esp"
    },
    {
      "iteration": 192,
      "energy": -0.9216695086585461,
      "backend": "low_esp"
    },
    {
      "iteration": 193,
      "energy": -0.9388221732685982,
      "backend": "low_esp"
    },
    {
      "iteration": 194,
      "energy": -0.9294239745047695,
      "backend": "low_esp"
    },
    {
      "iteration": 195,
      "energy": -0.9592629707075734,
      "backend": "low_esp"
    },
    {
      "iteration": 196,
      "energy": -0.9542188902729081,
      "backend": "low_esp"
    },
    {
      "iteration": 197,
      "energy": -0.9797077437173952,
      "backend": "low_esp"
    },
    {
      "iteration": 198,
      "energy": -0.9374950467392914,
      "backend": "low_esp"
    },
    {
      "iteration": 199,
      "energy": -0.9545595149635435,
      "backend": "low_esp"
    },
    {
      "iteration": 200,
      "energy": -0.9373013065479308,
      "backend": "low_esp"
    },
    {
      "iteration": 201,
      "energy": -0.96025614145946,
      "backend": "low_esp"
    },
    {
      "iteration": 202,
      "energy": -0.9456734745761937,
      "backend": "low_esp"
    },
    {
      "iteration": 203,
      "energy": -0.9436702359977637,
      "backend": "low_esp"
    },
    {
      "iteration": 204,
      "energy": -0.953151951324785,
      "backend": "low_esp"
    },
    {
      "iteration": 205,
      "energy": -0.9668345192418166,
      "backend": "low_esp"
    },
    {
      "iteration": 206,
      "energy": -0.9616410600156458,
      "backend": "low_esp"
    },
    {
      "iteration": 207,
      "energy": -0.9746402698605109,
      "backend": "low_esp"
    },
    {
      "iteration": 208,
      "energy": -0.9626158151784576,
      "backend": "low_esp"
    },
    {
      "iteration": 209,
      "energy": -0.9590971198651059,
      "backend": "low_esp"
    },
    {
      "iteration": 210,
      "energy": -0.9715912218588539,
      "backend": "low_esp"
    },
    {
      "iteration": 211,
      "energy": -0.9580781550222264,
      "backend": "low_esp"
    },
    {
      "iteration": 212,
      "energy": -0.965508793487307,
      "backend": "low_esp"
    },
    {
      "iteration": 213,
      "energy": -0.9526861280963725,
      "backend": "low_esp"
    },
    {
      "iteration": 214,
      "energy": -0.9748940712735816,
      "backend": "low_esp"
    },
    {
      "iteration": 215,
      "energy": -0.9292937358343306,
      "backend": "low_esp"
    },
    {
      "iteration": 216,
      "energy": -0.9732787803092715,
      "backend": "low_esp"
    },
    {
      "iteration": 217,
      "energy": -0.9568454202940049,
      "backend": "low_esp"
    },
    {
      "iteration": 218,
      "energy": -0.950646419063125,
      "backend": "low_esp"
    },
    {
      "iteration": 219,
      "energy": -0.960326589991695,
      "backend": "low_esp"
    },
    {
      "iteration": 220,
      "energy": -0.9664035119734351,
      "backend": "low_esp"
    },
    {
      "iteration": 221,
      "energy": -0.9657024229981442,
      "backend": "low_esp"
    },
    {
      "iteration": 222,
      "energy": -0.9866587776056065,
      "backend": "low_esp"
    },
    {
      "iteration": 223,
      "energy": -0.9640747515211723,
      "backend": "low_esp"
    },
    {
      "iteration": 224,
      "energy": -0.9549929214988826,
      "backend": "low_esp"
    },
    {
      "iteration": 225,
      "energy": -0.9699509579514041,
      "backend": "low_esp"
    },
    {
      "iteration": 226,
      "energy": -0.9658533003367746,
      "backend": "low_esp"
    },
    {
      "iteration": 227,
      "energy": -0.9643362376624776,
      "backend": "low_esp"
    },
    {
      "iteration": 228,
      "energy": -0.9342135454384426,
      "backend": "low_esp"
    },
    {
      "iteration": 229,
      "energy": -0.9739523090247036,
      "backend": "low_esp"
    },
    {
      "iteration": 230,
      "energy": -0.9893634106245633,
      "backend": "low_esp"
    },
    {
      "iteration": 231,
      "energy": -0.990480665301981,
      "backend": "low_esp"
    },
    {
      "iteration": 232,
      "energy": -0.9684881585600398,
      "backend": "low_esp"
    },
    {
      "iteration": 233,
      "energy": -0.9814363658680245,
      "backend": "low_esp"
    },
    {
      "iteration": 234,
      "energy": -0.9913988410928205,
      "backend": "low_esp"
    },
    {
      "iteration": 235,
      "energy": -0.9698703477021624,
      "backend": "low_esp"
    },
    {
      "iteration": 236,
      "energy": -0.9818759599617571,
      "backend": "low_esp"
    },
    {
      "iteration": 237,
      "energy": -0.9627478393546216,
      "backend": "low_esp"
    },
    {
      "iteration": 238,
      "energy": -0.9979053343697948,
      "backend": "low_esp"
    },
    {
      "iteration": 239,
      "energy": -0.9945219117424002,
      "backend": "low_esp"
    },
    {
      "iteration": 240,
      "energy": -0.9788134166500048,
      "backend": "low_esp"
    },
    {
      "iteration": 241,
      "energy": -0.9710300077421733,
      "backend": "low_esp"
    },
    {
      "iteration": 242,
      "energy": -0.9853887753562663,
      "backend": "low_esp"
    },
    {
      "iteration": 243,
      "energy": -0.9915879906572691,
      "backend": "low_esp"
    },
    {
      "iteration": 244,
      "energy": -0.9820802142752776,
      "backend": "low_esp"
    },
    {
      "iteration": 245,
      "energy": -0.9579939613672942,
      "backend": "low_esp"
    },
    {
      "iteration": 246,
      "energy": -0.9733513052350248,
      "backend": "low_esp"
    },
    {
      "iteration": 247,
      "energy": -0.9777150343425812,
      "backend": "low_esp"
    },
    {
      "iteration": 248,
      "energy": -0.9699542895158952,
      "backend": "low_esp"
    },
    {
      "iteration": 249,
      "energy": -0.9973134513584656,
      "backend": "low_esp"
    },
    {
      "iteration": 250,
      "energy": -0.9833945351801121,
      "backend": "low_esp"
    },
    {
      "iteration": 251,
      "energy": -0.9537528283383224,
      "backend": "low_esp"
    },
    {
      "iteration": 252,
      "energy": -0.9706961786658732,
      "backend": "low_esp"
    },
    {
      "iteration": 253,
      "energy": -0.9880350930327421,
      "backend": "low_esp"
    },
    {
      "iteration": 254,
      "energy": -1.0022660240299668,
      "backend": "low_esp"
    },
    {
      "iteration": 255,
      "energy": -0.9964208967396294,
      "backend": "low_esp"
    },
    {
      "iteration": 256,
      "energy": -0.9943762842829702,
      "backend": "low_esp"
    },
    {
      "iteration": 257,
      "energy": -0.9814230830875691,
      "backend": "low_esp"
    },
    {
      "iteration": 258,
      "energy": -0.9803862299534326,
      "backend": "low_esp"
    },
    {
      "iteration": 259,
      "energy": -0.9864375791495826,
      "backend": "low_esp"
    },
    {
      "iteration": 260,
      "energy": -0.9832887286262351,
      "backend": "low_esp"
    },
    {
      "iteration": 261,
      "energy": -0.9738598223672695,
      "backend": "low_esp"
    },
    {
      "iteration": 262,
      "energy": -0.990546265799239,
      "backend": "low_esp"
    },
    {
      "iteration": 263,
      "energy": -0.9843516069661007,
      "backend": "low_esp"
    },
    {
      "iteration": 264,
      "energy": -0.9898380296290945,
      "backend": "low_esp"
    },
    {
      "iteration": 265,
      "energy": -0.9858320281151279,
      "backend": "low_esp"
    },
    {
      "iteration": 266,
      "energy": -0.9683690107534896,
      "backend": "low_esp"
    },
    {
      "iteration": 267,
      "energy": -1.0041648601505313,
      "backend": "low_esp"
    },
    {
      "iteration": 268,
      "energy": -0.9937157318053094,
      "backend": "low_esp"
    },
    {
      "iteration": 269,
      "energy": -0.985972491251487,
      "backend": "low_esp"
    },
    {
      "iteration": 270,
      "energy": -0.9836249795388138,
      "backend": "low_esp"
    },
    {
      "iteration": 271,
      "energy": -0.9889873178138965,
      "backend": "low_esp"
    },
    {
      "iteration": 272,
      "energy": -0.9928850586543244,
      "backend": "low_esp"
    },
    {
      "iteration": 273,
      "energy": -0.988191713156961,
      "backend": "low_esp"
    },
    {
      "iteration": 274,
      "energy": -0.9920272639982164,
      "backend": "low_esp"
    },
    {
      "iteration": 275,
      "energy": -0.9979856248344197,
      "backend": "low_esp"
    },
    {
      "iteration": 276,
      "energy": -0.9883899130516363,
      "backend": "low_esp"
    },
    {
      "iteration": 277,
      "energy": -0.9827059727272305,
      "backend": "low_esp"
    },
    {
      "iteration": 278,
      "energy": -0.9945320428185076,
      "backend": "low_esp"
    },
    {
      "iteration": 279,
      "energy": -0.9884218980046691,
      "backend": "low_esp"
    },
    {
      "iteration": 280,
      "energy": -0.9722247252281601,
      "backend": "low_esp"
    },
    {
      "iteration": 281,
      "energy": -0.9743353808191721,
      "backend": "low_esp"
    },
    {
      "iteration": 282,
      "energy": -0.9824881349464059,
      "backend": "low_esp"
    },
    {
      "iteration": 283,
      "energy": -0.9843376552158699,
      "backend": "low_esp"
    },
    {
      "iteration": 284,
      "energy": -1.0025334547160802,
      "backend": "low_esp"
    },
    {
      "iteration": 285,
      "energy": -0.9833425266997526,
      "backend": "low_esp"
    },
    {
      "iteration": 286,
      "energy": -0.998857611155155,
      "backend": "low_esp"
    },
    {
      "iteration": 287,
      "energy": -0.9984990253171685,
      "backend": "low_esp"
    },
    {
      "iteration": 288,
      "energy": -0.9722275921950977,
      "backend": "low_esp"
    },
    {
      "iteration": 289,
      "energy": -0.9845138232762936,
      "backend": "low_esp"
    },
    {
      "iteration": 290,
      "energy": -1.0079661485738294,
      "backend": "low_esp"
    },
    {
      "iteration": 291,
      "energy": -0.9772966535015789,
      "backend": "low_esp"
    },
    {
      "iteration": 292,
      "energy": -0.9812003950334084,
      "backend": "low_esp"
    },
    {
      "iteration": 293,
      "energy": -0.9852109024656432,
      "backend": "low_esp"
    },
    {
      "iteration": 294,
      "energy": -0.9731593176948478,
      "backend": "low_esp"
    },
    {
      "iteration": 295,
      "energy": -0.985407927598276,
      "backend": "low_esp"
    },
    {
      "iteration": 296,
      "energy": -0.981525825955857,
      "backend": "low_esp"
    },
    {
      "iteration": 297,
      "energy": -0.9877133097031662,
      "backend": "low_esp"
    },
    {
      "iteration": 298,
      "energy": -0.995923135441813,
      "backend": "low_esp"
    },
    {
      "iteration": 299,
      "energy": -1.00435003758307,
      "backend": "low_esp"
    },
    {
      "iteration": 300,
      "energy": -0.996222494825332,
      "backend": "low_esp"
    },
    {
      "iteration": 301,
      "energy": -0.9962797501295901,
      "backend": "low_esp"
    },
    {
      "iteration": 302,
      "energy": -0.988800581347836,
      "backend": "low_esp"
    },
    {
      "iteration": 303,
      "energy": -0.9839440614624797,
      "backend": "low_esp"
    },
    {
      "iteration": 304,
      "energy": -0.9985243699091723,
      "backend": "low_esp"
    },
    {
      "iteration": 305,
      "energy": -0.9865792953811419,
      "backend": "low_esp"
    },
    {
      "iteration": 306,
      "energy": -0.9855063647296187,
      "backend": "low_esp"
    },
    {
      "iteration": 307,
      "energy": -0.9803607665976644,
      "backend": "low_esp"
    },
    {
      "iteration": 308,
      "energy": -0.9885332418063242,
      "backend": "low_esp"
    },
    {
      "iteration": 309,
      "energy": -0.9902624966686002,
      "backend": "low_esp"
    },
    {
      "iteration": 310,
      "energy": -0.9869481195190285,
      "backend": "low_esp"
    },
    {
      "iteration": 311,
      "energy": -1.0049989788912401,
      "backend": "low_esp"
    },
    {
      "iteration": 312,
      "energy": -0.9755802087106524,
      "backend": "low_esp"
    },
    {
      "iteration": 313,
      "energy": -0.9770467470119796,
      "backend": "low_esp"
    },
    {
      "iteration": 314,
      "energy": -1.0044897154489612,
      "backend": "low_esp"
    },
    {
      "iteration": 315,
      "energy": -0.9950331282686179,
      "backend": "low_esp"
    },
    {
      "iteration": 316,
      "energy": -0.9938347466302109,
      "backend": "low_esp"
    },
    {
      "iteration": 317,
      "energy": -1.004462428342354,
      "backend": "low_esp"
    },
    {
      "iteration": 318,
      "energy": -0.9930767808838162,
      "backend": "low_esp"
    },
    {
      "iteration": 319,
      "energy": -0.9854815855096049,
      "backend": "low_esp"
    },
    {
      "iteration": 320,
      "energy": -0.9887476640830599,
      "backend": "low_esp"
    },
    {
      "iteration": 321,
      "energy": -0.9927401590117547,
      "backend": "low_esp"
    },
    {
      "iteration": 322,
      "energy": -0.9850603332492974,
      "backend": "low_esp"
    },
    {
      "iteration": 323,
      "energy": -0.9796159170946377,
      "backend": "low_esp"
    },
    {
      "iteration": 324,
      "energy": -0.9841424956068212,
      "backend": "low_esp"
    },
    {
      "iteration": 325,
      "energy": -0.9790540229041533,
      "backend": "low_esp"
    },
    {
      "iteration": 326,
      "energy": -0.9990645710368046,
      "backend": "low_esp"
    },
    {
      "iteration": 327,
      "energy": -1.0011632164717177,
      "backend": "low_esp"
    },
    {
      "iteration": 328,
      "energy": -1.0067790760059274,
      "backend": "low_esp"
    },
    {
      "iteration": 329,
      "energy": -0.9858855172642103,
      "backend": "low_esp"
    },
    {
      "iteration": 330,
      "energy": -0.9949370916063764,
      "backend": "low_esp"
    },
    {
      "iteration": 331,
      "energy": -0.9827159495200793,
      "backend": "low_esp"
    },
    {
      "iteration": 332,
      "energy": -0.9769443289948531,
      "backend": "low_esp"
    },
    {
      "iteration": 333,
      "energy": -0.9987314708753414,
      "backend": "low_esp"
    },
    {
      "iteration": 334,
      "energy": -0.9941156593039588,
      "backend": "low_esp"
    },
    {
      "iteration": 335,
      "energy": -0.9864441396733046,
      "backend": "low_esp"
    },
    {
      "iteration": 336,
      "energy": -0.9909690319795833,
      "backend": "low_esp"
    },
    {
      "iteration": 337,
      "energy": -0.9954982706431776,
      "backend": "low_esp"
    },
    {
      "iteration": 338,
      "energy": -0.9881942032030127,
      "backend": "low_esp"
    },
    {
      "iteration": 339,
      "energy": -1.006735218965598,
      "backend": "low_esp"
    },
    {
      "iteration": 340,
      "energy": -0.98981255419668,
      "backend": "low_esp"
    },
    {
      "iteration": 341,
      "energy": -0.9951191287412884,
      "backend": "low_esp"
    },
    {
      "iteration": 342,
      "energy": -0.9939876563683883,
      "backend": "low_esp"
    },
    {
      "iteration": 343,
      "energy": -0.9979380290259641,
      "backend": "low_esp"
    },
    {
      "iteration": 344,
      "energy": -0.9913901529197614,
      "backend": "low_esp"
    },
    {
      "iteration": 345,
      "energy": -1.0014504291507254,
      "backend": "low_esp"
    },
    {
      "iteration": 346,
      "energy": -0.9891678694099518,
      "backend": "low_esp"
    },
    {
      "iteration": 347,
      "energy": -0.993606775671939,
      "backend": "low_esp"
    },
    {
      "iteration": 348,
      "energy": -0.9874074225324254,
      "backend": "low_esp"
    },
    {
      "iteration": 349,
      "energy": -0.984669809070654,
      "backend": "low_esp"
    },
    {
      "iteration": 350,
      "energy": -1.0001498768470904,
      "backend": "low_esp"
    },
    {
      "iteration": 351,
      "energy": -0.9897323510664783,
      "backend": "low_esp"
    },
    {
      "iteration": 352,
      "energy": -0.9945382420729942,
      "backend": "low_esp"
    },
    {
      "iteration": 353,
      "energy": -0.9979449713401051,
      "backend": "low_esp"
    },
    {
      "iteration": 354,
      "energy": -0.9830833462441706,
      "backend": "low_esp"
    },
    {
      "iteration": 355,
      "energy": -0.9957412082946722,
      "backend": "low_esp"
    },
    {
      "iteration": 356,
      "energy": -0.9839576066155509,
      "backend": "low_esp"
    },
    {
      "iteration": 357,
      "energy": -0.9801340572081642,
      "backend": "low_esp"
    },
    {
      "iteration": 358,
      "energy": -0.9998277652958214,
      "backend": "low_esp"
    },
    {
      "iteration": 359,
      "energy": -0.9930820991960438,
      "backend": "low_esp"
    },
    {
      "iteration": 360,
      "energy": -0.9764737517103658,
      "backend": "low_esp"
    },
    {
      "iteration": 361,
      "energy": -0.9806222846151118,
      "backend": "low_esp"
    },
    {
      "iteration": 362,
      "energy": -0.9872383976550199,
      "backend": "low_esp"
    },
    {
      "iteration": 363,
      "energy": -0.9890239829953987,
      "backend": "low_esp"
    },
    {
      "iteration": 364,
      "energy": -0.9844080107361397,
      "backend": "low_esp"
    },
    {
      "iteration": 365,
      "energy": -0.9983291201198701,
      "backend": "low_esp"
    },
    {
      "iteration": 366,
      "energy": -0.9855209186331917,
      "backend": "low_esp"
    },
    {
      "iteration": 367,
      "energy": -0.9953194695578104,
      "backend": "low_esp"
    },
    {
      "iteration": 368,
      "energy": -1.003477577579369,
      "backend": "low_esp"
    },
    {
      "iteration": 369,
      "energy": -0.9867177337491916,
      "backend": "low_esp"
    },
    {
      "iteration": 370,
      "energy": -0.9966329393501913,
      "backend": "low_esp"
    },
    {
      "iteration": 371,
      "energy": -0.9972301973382686,
      "backend": "low_esp"
    },
    {
      "iteration": 372,
      "energy": -1.001174041400386,
      "backend": "low_esp"
    },
    {
      "iteration": 373,
      "energy": -1.02218072532693,
      "backend": "low_esp"
    },
    {
      "iteration": 374,
      "energy": -0.9897205008431573,
      "backend": "low_esp"
    },
    {
      "iteration": 375,
      "energy": -0.9911830268030245,
      "backend": "low_esp"
    },
    {
      "iteration": 376,
      "energy": -0.9840499925440797,
      "backend": "low_esp"
    },
    {
      "iteration": 377,
      "energy": -1.0002220818995928,
      "backend": "low_esp"
    },
    {
      "iteration": 378,
      "energy": -0.9867603079096547,
      "backend": "low_esp"
    },
    {
      "iteration": 379,
      "energy": -1.010653086636853,
      "backend": "low_esp"
    },
    {
      "iteration": 380,
      "energy": -0.9802657594998079,
      "backend": "low_esp"
    },
    {
      "iteration": 381,
      "energy": -0.9893760020576801,
      "backend": "low_esp"
    },
    {
      "iteration": 382,
      "energy": -0.9989363290295452,
      "backend": "low_esp"
    },
    {
      "iteration": 383,
      "energy": -1.0043430555739095,
      "backend": "low_esp"
    },
    {
      "iteration": 384,
      "energy": -1.0080617479736267,
      "backend": "low_esp"
    },
    {
      "iteration": 385,
      "energy": -0.9743937888860054,
      "backend": "low_esp"
    },
    {
      "iteration": 386,
      "energy": -0.9820156664651224,
      "backend": "low_esp"
    },
    {
      "iteration": 387,
      "energy": -1.0056601259555067,
      "backend": "low_esp"
    },
    {
      "iteration": 388,
      "energy": -0.9767359395452175,
      "backend": "low_esp"
    },
    {
      "iteration": 389,
      "energy": -1.0041489245887092,
      "backend": "low_esp"
    },
    {
      "iteration": 390,
      "energy": -0.9864668641079812,
      "backend": "low_esp"
    },
    {
      "iteration": 391,
      "energy": -0.9936664021328071,
      "backend": "low_esp"
    },
    {
      "iteration": 392,
      "energy": -0.9943481108989005,
      "backend": "low_esp"
    },
    {
      "iteration": 393,
      "energy": -0.9931742596172446,
      "backend": "low_esp"
    },
    {
      "iteration": 394,
      "energy": -0.9910768656557856,
      "backend": "low_esp"
    },
    {
      "iteration": 395,
      "energy": -0.9925293644448949,
      "backend": "low_esp"
    },
    {
      "iteration": 396,
      "energy": -0.9803820236942201,
      "backend": "low_esp"
    },
    {
      "iteration": 397,
      "energy": -0.9912415858794122,
      "backend": "low_esp"
    },
    {
      "iteration": 398,
      "energy": -0.9844816467424825,
      "backend": "low_esp"
    },
    {
      "iteration": 399,
      "energy": -1.0136943912922949,
      "backend": "low_esp"
    },
    {
      "iteration": 400,
      "energy": -0.9933663469042345,
      "backend": "low_esp"
    },
    {
      "iteration": 401,
      "energy": -0.9867137525807312,
      "backend": "low_esp"
    },
    {
      "iteration": 402,
      "energy": -0.9846988721962985,
      "backend": "low_esp"
    },
    {
      "iteration": 403,
      "energy": -1.0010623325210026,
      "backend": "low_esp"
    },
    {
      "iteration": 404,
      "energy": -0.987683538222029,
      "backend": "low_esp"
    },
    {
      "iteration": 405,
      "energy": -0.980357883534686,
      "backend": "low_esp"
    },
    {
      "iteration": 406,
      "energy": -0.9879883726348457,
      "backend": "low_esp"
    },
    {
      "iteration": 407,
      "energy": -0.9876401456763831,
      "backend": "low_esp"
    },
    {
      "iteration": 408,
      "energy": -0.9901014730659202,
      "backend": "low_esp"
    },
    {
      "iteration": 409,
      "energy": -0.977505165630948,
      "backend": "low_esp"
    },
    {
      "iteration": 410,
      "energy": -0.9892592210475826,
      "backend": "low_esp"
    },
    {
      "iteration": 411,
      "energy": -0.9885285931635892,
      "backend": "low_esp"
    },
    {
      "iteration": 412,
      "energy": -0.9916529438388415,
      "backend": "low_esp"
    },
    {
      "iteration": 413,
      "energy": -0.9878477235906433,
      "backend": "low_esp"
    },
    {
      "iteration": 414,
      "energy": -0.9805706118843932,
      "backend": "low_esp"
    },
    {
      "iteration": 415,
      "energy": -0.9821841344820506,
      "backend": "low_esp"
    },
    {
      "iteration": 416,
      "energy": -0.9804994431846361,
      "backend": "low_esp"
    },
    {
      "iteration": 417,
      "energy": -0.9949147579567097,
      "backend": "low_esp"
    },
    {
      "iteration": 418,
      "energy": -0.9926509167429913,
      "backend": "low_esp"
    },
    {
      "iteration": 419,
      "energy": -0.9839286256051647,
      "backend": "low_esp"
    },
    {
      "iteration": 420,
      "energy": -0.9905521556132926,
      "backend": "low_esp"
    },
    {
      "iteration": 421,
      "energy": -0.9984636050375271,
      "backend": "low_esp"
    },
    {
      "iteration": 422,
      "energy": -1.001545164056571,
      "backend": "low_esp"
    },
    {
      "iteration": 423,
      "energy": -1.0036085142657818,
      "backend": "low_esp"
    },
    {
      "iteration": 424,
      "energy": -0.9888077394557179,
      "backend": "low_esp"
    },
    {
      "iteration": 425,
      "energy": -0.9904018792289039,
      "backend": "low_esp"
    },
    {
      "iteration": 426,
      "energy": -0.996281025297224,
      "backend": "low_esp"
    },
    {
      "iteration": 427,
      "energy": -0.9960700983874453,
      "backend": "low_esp"
    },
    {
      "iteration": 428,
      "energy": -0.991364355178894,
      "backend": "low_esp"
    },
    {
      "iteration": 429,
      "energy": -0.9939067229889866,
      "backend": "low_esp"
    },
    {
      "iteration": 430,
      "energy": -0.9832152236276752,
      "backend": "low_esp"
    },
    {
      "iteration": 431,
      "energy": -1.0058348346588557,
      "backend": "low_esp"
    },
    {
      "iteration": 432,
      "energy": -0.9767103207640095,
      "backend": "low_esp"
    },
    {
      "iteration": 433,
      "energy": -1.0096139232904762,
      "backend": "low_esp"
    },
    {
      "iteration": 434,
      "energy": -0.9855691769765419,
      "backend": "low_esp"
    },
    {
      "iteration": 435,
      "energy": -0.9986837512106141,
      "backend": "low_esp"
    },
    {
      "iteration": 436,
      "energy": -0.9874750176691178,
      "backend": "low_esp"
    },
    {
      "iteration": 437,
      "energy": -0.9835813261834501,
      "backend": "low_esp"
    },
    {
      "iteration": 438,
      "energy": -0.9945058077606876,
      "backend": "low_esp"
    },
    {
      "iteration": 439,
      "energy": -0.9936408366766152,
      "backend": "low_esp"
    },
    {
      "iteration": 440,
      "energy": -0.9897506359437384,
      "backend": "low_esp"
    },
    {
      "iteration": 441,
      "energy": -1.0030079776846665,
      "backend": "low_esp"
    },
    {
      "iteration": 442,
      "energy": -1.0109792567971994,
      "backend": "low_esp"
    },
    {
      "iteration": 443,
      "energy": -0.9827040102786893,
      "backend": "low_esp"
    },
    {
      "iteration": 444,
      "energy": -0.9944435968770955,
      "backend": "low_esp"
    },
    {
      "iteration": 445,
      "energy": -0.9727454843061382,
      "backend": "low_esp"
    },
    {
      "iteration": 446,
      "energy": -0.9906273992409993,
      "backend": "low_esp"
    },
    {
      "iteration": 447,
      "energy": -0.9930535891587896,
      "backend": "low_esp"
    },
    {
      "iteration": 448,
      "energy": -1.0023096696485798,
      "backend": "low_esp"
    },
    {
      "iteration": 449,
      "energy": -0.9961121172672628,
      "backend": "low_esp"
    },
    {
      "iteration": 450,
      "energy": -0.9843354349844607,
      "backend": "low_esp"
    },
    {
      "iteration": 451,
      "energy": -0.9915780723447402,
      "backend": "low_esp"
    },
    {
      "iteration": 452,
      "energy": -0.9708157742918404,
      "backend": "low_esp"
    },
    {
      "iteration": 453,
      "energy": -0.9821755737791948,
      "backend": "low_esp"
    },
    {
      "iteration": 454,
      "energy": -0.9928412037936246,
      "backend": "low_esp"
    },
    {
      "iteration": 455,
      "energy": -1.0059987359566407,
      "backend": "low_esp"
    },
    {
      "iteration": 456,
      "energy": -0.9904525046399939,
      "backend": "low_esp"
    },
    {
      "iteration": 457,
      "energy": -0.9829533866669644,
      "backend": "low_esp"
    },
    {
      "iteration": 458,
      "energy": -0.9938630451887058,
      "backend": "low_esp"
    },
    {
      "iteration": 459,
      "energy": -0.9941012149590077,
      "backend": "low_esp"
    },
    {
      "iteration": 460,
      "energy": -0.9873330863275165,
      "backend": "low_esp"
    },
    {
      "iteration": 461,
      "energy": -1.002597440287868,
      "backend": "low_esp"
    },
    {
      "iteration": 462,
      "energy": -0.9862695613172495,
      "backend": "low_esp"
    },
    {
      "iteration": 463,
      "energy": -0.9807947684390141,
      "backend": "low_esp"
    },
    {
      "iteration": 464,
      "energy": -0.995676229078026,
      "backend": "low_esp"
    },
    {
      "iteration": 465,
      "energy": -0.9865652338315042,
      "backend": "low_esp"
    },
    {
      "iteration": 466,
      "energy": -0.9844337851330808,
      "backend": "low_esp"
    },
    {
      "iteration": 467,
      "energy": -0.9812131317031789,
      "backend": "low_esp"
    },
    {
      "iteration": 468,
      "energy": -0.9978563260714338,
      "backend": "low_esp"
    },
    {
      "iteration": 469,
      "energy": -0.989502518399853,
      "backend": "low_esp"
    },
    {
      "iteration": 470,
      "energy": -1.0017863369291702,
      "backend": "low_esp"
    },
    {
      "iteration": 471,
      "energy": -0.9975652962336088,
      "backend": "low_esp"
    },
    {
      "iteration": 472,
      "energy": -1.007904091964703,
      "backend": "low_esp"
    },
    {
      "iteration": 473,
      "energy": -0.9832124845072744,
      "backend": "low_esp"
    },
    {
      "iteration": 474,
      "energy": -0.9945942575499777,
      "backend": "low_esp"
    },
    {
      "iteration": 475,
      "energy": -0.9891251562474344,
      "backend": "low_esp"
    },
    {
      "iteration": 476,
      "energy": -0.9942973049969542,
      "backend": "low_esp"
    },
    {
      "iteration": 477,
      "energy": -0.9874086933701239,
      "backend": "low_esp"
    },
    {
      "iteration": 478,
      "energy": -0.9737892343700001,
      "backend": "low_esp"
    },
    {
      "iteration": 479,
      "energy": -1.0000361775488922,
      "backend": "low_esp"
    },
    {
      "iteration": 480,
      "energy": -0.9950592972514202,
      "backend": "low_esp"
    },
    {
      "iteration": 481,
      "energy": -1.0146265087438318,
      "backend": "low_esp"
    },
    {
      "iteration": 482,
      "energy": -0.9783010937643801,
      "backend": "low_esp"
    },
    {
      "iteration": 483,
      "energy": -0.987149492638464,
      "backend": "low_esp"
    },
    {
      "iteration": 484,
      "energy": -0.9933505478747822,
      "backend": "low_esp"
    },
    {
      "iteration": 485,
      "energy": -0.9753752756976005,
      "backend": "low_esp"
    },
    {
      "iteration": 486,
      "energy": -0.988498677482685,
      "backend": "low_esp"
    },
    {
      "iteration": 487,
      "energy": -0.9887551356568564,
      "backend": "low_esp"
    },
    {
      "iteration": 488,
      "energy": -0.9701850755712808,
      "backend": "low_esp"
    },
    {
      "iteration": 489,
      "energy": -0.9872321103207314,
      "backend": "low_esp"
    },
    {
      "iteration": 490,
      "energy": -0.986803650968842,
      "backend": "low_esp"
    },
    {
      "iteration": 491,
      "energy": -0.9755813165936748,
      "backend": "low_esp"
    },
    {
      "iteration": 492,
      "energy": -0.9902528057652127,
      "backend": "low_esp"
    },
    {
      "iteration": 493,
      "energy": -0.991041681423641,
      "backend": "low_esp"
    },
    {
      "iteration": 494,
      "energy": -0.9831476510950072,
      "backend": "low_esp"
    },
    {
      "iteration": 495,
      "energy": -0.9725595134843669,
      "backend": "low_esp"
    },
    {
      "iteration": 496,
      "energy": -0.9709970778238923,
      "backend": "low_esp"
    },
    {
      "iteration": 497,
      "energy": -0.9863028654967695,
      "backend": "low_esp"
    },
    {
      "iteration": 498,
      "energy": -1.004704830308434,
      "backend": "low_esp"
    },
    {
      "iteration": 499,
      "energy": -0.983963492072204,
      "backend": "low_esp"
    },
    {
      "iteration": 500,
      "energy": -0.9801006627022254,
      "backend": "low_esp"
    },
    {
      "iteration": 501,
      "energy": -0.9914521643602616,
      "backend": "low_esp"
    },
    {
      "iteration": 502,
      "energy": -0.9966096027430965,
      "backend": "low_esp"
    },
    {
      "iteration": 503,
      "energy": -0.9972277483726572,
      "backend": "low_esp"
    },
    {
      "iteration": 504,
      "energy": -1.002954264449728,
      "backend": "low_esp"
    },
    {
      "iteration": 505,
      "energy": -0.9941579810649102,
      "backend": "low_esp"
    },
    {
      "iteration": 506,
      "energy": -0.9858887593075685,
      "backend": "low_esp"
    },
    {
      "iteration": 507,
      "energy": -0.996675494105996,
      "backend": "low_esp"
    },
    {
      "iteration": 508,
      "energy": -0.9932234844366649,
      "backend": "low_esp"
    },
    {
      "iteration": 509,
      "energy": -0.9865295237613546,
      "backend": "low_esp"
    },
    {
      "iteration": 510,
      "energy": -0.9880442042956794,
      "backend": "low_esp"
    },
    {
      "iteration": 511,
      "energy": -0.993815848225376,
      "backend": "low_esp"
    },
    {
      "iteration": 512,
      "energy": -0.9964044075187274,
      "backend": "low_esp"
    },
    {
      "iteration": 513,
      "energy": -0.9836262273585812,
      "backend": "low_esp"
    },
    {
      "iteration": 514,
      "energy": -1.0048712775763275,
      "backend": "low_esp"
    },
    {
      "iteration": 515,
      "energy": -0.9823342277938873,
      "backend": "low_esp"
    },
    {
      "iteration": 516,
      "energy": -0.9852546126925433,
      "backend": "low_esp"
    },
    {
      "iteration": 517,
      "energy": -0.982760636808888,
      "backend": "low_esp"
    },
    {
      "iteration": 518,
      "energy": -0.9765933162754782,
      "backend": "low_esp"
    },
    {
      "iteration": 519,
      "energy": -0.9938681249615208,
      "backend": "low_esp"
    },
    {
      "iteration": 520,
      "energy": -0.9778727480511868,
      "backend": "low_esp"
    },
    {
      "iteration": 521,
      "energy": -0.9824603962259888,
      "backend": "low_esp"
    },
    {
      "iteration": 522,
      "energy": -1.0027369972956997,
      "backend": "low_esp"
    },
    {
      "iteration": 523,
      "energy": -0.9997618880167896,
      "backend": "low_esp"
    },
    {
      "iteration": 524,
      "energy": -0.9961782375244047,
      "backend": "low_esp"
    },
    {
      "iteration": 525,
      "energy": -1.0102549201211242,
      "backend": "low_esp"
    },
    {
      "iteration": 526,
      "energy": -0.9905386118872687,
      "backend": "low_esp"
    },
    {
      "iteration": 527,
      "energy": -0.9826684349511665,
      "backend": "low_esp"
    },
    {
      "iteration": 528,
      "energy": -0.99406148258035,
      "backend": "low_esp"
    },
    {
      "iteration": 529,
      "energy": -0.9846632001183564,
      "backend": "low_esp"
    },
    {
      "iteration": 530,
      "energy": -0.9890516674280045,
      "backend": "low_esp"
    },
    {
      "iteration": 531,
      "energy": -0.9832267369924619,
      "backend": "low_esp"
    },
    {
      "iteration": 532,
      "energy": -0.9998029832598725,
      "backend": "low_esp"
    },
    {
      "iteration": 533,
      "energy": -0.9881929792375006,
      "backend": "low_esp"
    },
    {
      "iteration": 534,
      "energy": -0.9984198066125609,
      "backend": "low_esp"
    },
    {
      "iteration": 535,
      "energy": -0.9878806474628342,
      "backend": "low_esp"
    },
    {
      "iteration": 536,
      "energy": -0.9981728914092285,
      "backend": "low_esp"
    },
    {
      "iteration": 537,
      "energy": -0.9894225469464955,
      "backend": "low_esp"
    },
    {
      "iteration": 538,
      "energy": -0.9958588646155282,
      "backend": "low_esp"
    },
    {
      "iteration": 539,
      "energy": -0.9819097160072515,
      "backend": "low_esp"
    },
    {
      "iteration": 540,
      "energy": -0.9878408445235681,
      "backend": "low_esp"
    },
    {
      "iteration": 541,
      "energy": -0.9953270211537241,
      "backend": "low_esp"
    },
    {
      "iteration": 542,
      "energy": -0.9977973666117206,
      "backend": "low_esp"
    },
    {
      "iteration": 543,
      "energy": -0.9891624355716195,
      "backend": "low_esp"
    },
    {
      "iteration": 544,
      "energy": -0.9776365893516396,
      "backend": "low_esp"
    },
    {
      "iteration": 545,
      "energy": -0.9824406549619493,
      "backend": "low_esp"
    },
    {
      "iteration": 546,
      "energy": -0.988627750566768,
      "backend": "low_esp"
    },
    {
      "iteration": 547,
      "energy": -1.0466744340495806,
      "backend": "high_esp"
    },
    {
      "iteration": 548,
      "energy": -1.0650285948661624,
      "backend": "high_esp"
    },
    {
      "iteration": 549,
      "energy": -1.0419480807816544,
      "backend": "high_esp"
    },
    {
      "iteration": 550,
      "energy": -1.0444157889087209,
      "backend": "high_esp"
    },
    {
      "iteration": 551,
      "energy": -1.0573134962179038,
      "backend": "high_esp"
    },
    {
      "iteration": 552,
      "energy": -1.0667777557911082,
      "backend": "high_esp"
    },
    {
      "iteration": 553,
      "energy": -1.0455443877263693,
      "backend": "high_esp"
    },
    {
      "iteration": 554,
      "energy": -1.0503041820099552,
      "backend": "high_esp"
    },
    {
      "iteration": 555,
      "energy": -1.0565972606739098,
      "backend": "high_esp"
    },
    {
      "iteration": 556,
      "energy": -1.062085040597592,
      "backend": "high_esp"
    },
    {
      "iteration": 557,
      "energy": -1.0522621158625312,
      "backend": "high_esp"
    },
    {
      "iteration": 558,
      "energy": -1.0295019355529638,
      "backend": "high_esp"
    },
    {
      "iteration": 559,
      "energy": -1.0479814873766777,
      "backend": "high_esp"
    },
    {
      "iteration": 560,
      "energy": -1.0515671773668471,
      "backend": "high_esp"
    },
    {
      "iteration": 561,
      "energy": -1.0508077505346447,
      "backend": "high_esp"
    },
    {
      "iteration": 562,
      "energy": -1.0399837363525108,
      "backend": "high_esp"
    },
    {
      "iteration": 563,
      "energy": -1.0405247984670547,
      "backend": "high_esp"
    },
    {
      "iteration": 564,
      "energy": -1.0537806318291814,
      "backend": "high_esp"
    },
    {
      "iteration": 565,
      "energy": -1.0310362376663538,
      "backend": "high_esp"
    },
    {
      "iteration": 566,
      "energy": -1.0383923401184862,
      "backend": "high_esp"
    },
    {
      "iteration": 567,
      "energy": -1.0450583199662675,
      "backend": "high_esp"
    },
    {
      "iteration": 568,
      "energy": -1.0567150397997167,
      "backend": "high_esp"
    },
    {
      "iteration": 569,
      "energy": -1.0319671594016402,
      "backend": "high_esp"
    },
    {
      "iteration": 570,
      "energy": -1.0433876114575986,
      "backend": "high_esp"
    },
    {
      "iteration": 571,
      "energy": -1.045611655335111,
      "backend": "high_esp"
    },
    {
      "iteration": 572,
      "energy": -1.0461854364664784,
      "backend": "high_esp"
    },
    {
      "iteration": 573,
      "energy": -1.048422237677506,
      "backend": "high_esp"
    },
    {
      "iteration": 574,
      "energy": -1.0478206961251302,
      "backend": "high_esp"
    },
    {
      "iteration": 575,
      "energy": -1.062537076005332,
      "backend": "high_esp"
    },
    {
      "iteration": 576,
      "energy": -1.0449091286101186,
      "backend": "high_esp"
    },
    {
      "iteration": 577,
      "energy": -1.04896225445676,
      "backend": "high_esp"
    },
    {
      "iteration": 578,
      "energy": -1.0433496635025474,
      "backend": "high_esp"
    },
    {
      "iteration": 579,
      "energy": -1.05266003949437,
      "backend": "high_esp"
    },
    {
      "iteration": 580,
      "energy": -1.0360942116026437,
      "backend": "high_esp"
    },
    {
      "iteration": 581,
      "energy": -1.0568340982577296,
      "backend": "high_esp"
    },
    {
      "iteration": 582,
      "energy": -1.0558404836111872,
      "backend": "high_esp"
    },
    {
      "iteration": 583,
      "energy": -1.0461809495010783,
      "backend": "high_esp"
    },
    {
      "iteration": 584,
      "energy": -1.0428078470295867,
      "backend": "high_esp"
    },
    {
      "iteration": 585,
      "energy": -1.050833974076557,
      "backend": "high_esp"
    },
    {
      "iteration": 586,
      "energy": -1.0447778133114418,
      "backend": "high_esp"
    },
    {
      "iteration": 587,
      "energy": -1.0389858012715654,
      "backend": "high_esp"
    },
    {
      "iteration": 588,
      "energy": -1.0468563494961638,
      "backend": "high_esp"
    },
    {
      "iteration": 589,
      "energy": -1.036311483972916,
      "backend": "high_esp"
    },
    {
      "iteration": 590,
      "energy": -1.054920771774917,
      "backend": "high_esp"
    },
    {
      "iteration": 591,
      "energy": -1.040779952651224,
      "backend": "high_esp"
    },
    {
      "iteration": 592,
      "energy": -1.0565133413892165,
      "backend": "high_esp"
    },
    {
      "iteration": 593,
      "energy": -1.0429047149234552,
      "backend": "high_esp"
    },
    {
      "iteration": 594,
      "energy": -1.037312504967812,
      "backend": "high_esp"
    },
    {
      "iteration": 595,
      "energy": -1.0498256547512361,
      "backend": "high_esp"
    },
    {
      "iteration": 596,
      "energy": -1.0603081099255411,
      "backend": "high_esp"
    },
    {
      "iteration": 597,
      "energy": -1.041509314029435,
      "backend": "high_esp"
    },
    {
      "iteration": 598,
      "energy": -1.045397435013091,
      "backend": "high_esp"
    },
    {
      "iteration": 599,
      "energy": -1.0352975252116106,
      "backend": "high_esp"
    },
    {
      "iteration": 600,
      "energy": -1.0398909844254771,
      "backend": "high_esp"
    },
    {
      "iteration": 601,
      "energy": -1.0551595206663307,
      "backend": "high_esp"
    },
    {
      "iteration": 602,
      "energy": -1.0295496244077922,
      "backend": "high_esp"
    },
    {
      "iteration": 603,
      "energy": -1.0527073163960796,
      "backend": "high_esp"
    },
    {
      "iteration": 604,
      "energy": -1.0397813189029397,
      "backend": "high_esp"
    },
    {
      "iteration": 605,
      "energy": -1.0567370633329074,
      "backend": "high_esp"
    },
    {
      "iteration": 606,
      "energy": -1.0445234690896648,
      "backend": "high_esp"
    },
    {
      "iteration": 607,
      "energy": -1.0366286690789637,
      "backend": "high_esp"
    },
    {
      "iteration": 608,
      "energy": -1.0414280154645457,
      "backend": "high_esp"
    },
    {
      "iteration": 609,
      "energy": -1.0606602220971948,
      "backend": "high_esp"
    },
    {
      "iteration": 610,
      "energy": -1.0533158274654835,
      "backend": "high_esp"
    },
    {
      "iteration": 611,
      "energy": -1.0531475045896699,
      "backend": "high_esp"
    },
    {
      "iteration": 612,
      "energy": -1.0398006940389015,
      "backend": "high_esp"
    },
    {
      "iteration": 613,
      "energy": -1.0450887149711066,
      "backend": "high_esp"
    },
    {
      "iteration": 614,
      "energy": -1.0516805472115291,
      "backend": "high_esp"
    },
    {
      "iteration": 615,
      "energy": -1.0445648317270584,
      "backend": "high_esp"
    },
    {
      "iteration": 616,
      "energy": -1.0418002997349252,
      "backend": "high_esp"
    },
    {
      "iteration": 617,
      "energy": -1.0490091526377647,
      "backend": "high_esp"
    },
    {
      "iteration": 618,
      "energy": -1.034129892622322,
      "backend": "high_esp"
    },
    {
      "iteration": 619,
      "energy": -1.0414921036441804,
      "backend": "high_esp"
    },
    {
      "iteration": 620,
      "energy": -1.0479367938515605,
      "backend": "high_esp"
    },
    {
      "iteration": 621,
      "energy": -1.044685040271084,
      "backend": "high_esp"
    },
    {
      "iteration": 622,
      "energy": -1.0449796893972063,
      "backend": "high_esp"
    },
    {
      "iteration": 623,
      "energy": -1.0527614219749053,
      "backend": "high_esp"
    },
    {
      "iteration": 624,
      "energy": -1.0413993110221789,
      "backend": "high_esp"
    },
    {
      "iteration": 625,
      "energy": -1.0456378901361503,
      "backend": "high_esp"
    },
    {
      "iteration": 626,
      "energy": -1.0538346282262205,
      "backend": "high_esp"
    },
    {
      "iteration": 627,
      "energy": -1.0398543344446456,
      "backend": "high_esp"
    },
    {
      "iteration": 628,
      "energy": -1.0515183953335756,
      "backend": "high_esp"
    },
    {
      "iteration": 629,
      "energy": -1.0478665280906159,
      "backend": "high_esp"
    },
    {
      "iteration": 630,
      "energy": -1.0547029845971965,
      "backend": "high_esp"
    },
    {
      "iteration": 631,
      "energy": -1.041512910601176,
      "backend": "high_esp"
    },
    {
      "iteration": 632,
      "energy": -1.045318388472889,
      "backend": "high_esp"
    },
    {
      "iteration": 633,
      "energy": -1.0498359874153804,
      "backend": "high_esp"
    },
    {
      "iteration": 634,
      "energy": -1.0439826443646865,
      "backend": "high_esp"
    },
    {
      "iteration": 635,
      "energy": -1.0629986968258125,
      "backend": "high_esp"
    },
    {
      "iteration": 636,
      "energy": -1.050835081851333,
      "backend": "high_esp"
    },
    {
      "iteration": 637,
      "energy": -1.0462618624976225,
      "backend": "high_esp"
    },
    {
      "iteration": 638,
      "energy": -1.0436462313010688,
      "backend": "high_esp"
    },
    {
      "iteration": 639,
      "energy": -1.0468477191727281,
      "backend": "high_esp"
    },
    {
      "iteration": 640,
      "energy": -1.043743239416637,
      "backend": "high_esp"
    },
    {
      "iteration": 641,
      "energy": -1.0439287983748968,
      "backend": "high_esp"
    },
    {
      "iteration": 642,
      "energy": -1.0397739149326424,
      "backend": "high_esp"
    },
    {
      "iteration": 643,
      "energy": -1.0444263869655486,
      "backend": "high_esp"
    },
    {
      "iteration": 644,
      "energy": -1.0198194037572206,
      "backend": "high_esp"
    },
    {
      "iteration": 645,
      "energy": -1.0372937644857623,
      "backend": "high_esp"
    },
    {
      "iteration": 646,
      "energy": -1.0505287374336556,
      "backend": "high_esp"
    },
    {
      "iteration": 647,
      "energy": -1.0604320018569635,
      "backend": "high_esp"
    },
    {
      "iteration": 648,
      "energy": -1.0503268335909666,
      "backend": "high_esp"
    },
    {
      "iteration": 649,
      "energy": -1.0493192887777678,
      "backend": "high_esp"
    },
    {
      "iteration": 650,
      "energy": -1.044922072434406,
      "backend": "high_esp"
    },
    {
      "iteration": 651,
      "energy": -1.0484952564154422,
      "backend": "high_esp"
    },
    {
      "iteration": 652,
      "energy": -1.030129358861196,
      "backend": "high_esp"
    },
    {
      "iteration": 653,
      "energy": -1.052620917767013,
      "backend": "high_esp"
    },
    {
      "iteration": 654,
      "energy": -1.0479849189115538,
      "backend": "high_esp"
    },
    {
      "iteration": 655,
      "energy": -1.05617697604374,
      "backend": "high_esp"
    },
    {
      "iteration": 656,
      "energy": -1.036645585566104,
      "backend": "high_esp"
    },
    {
      "iteration": 657,
      "energy": -1.0470952554103734,
      "backend": "high_esp"
    },
    {
      "iteration": 658,
      "energy": -1.0567573249280615,
      "backend": "high_esp"
    },
    {
      "iteration": 659,
      "energy": -1.0348815641625657,
      "backend": "high_esp"
    },
    {
      "iteration": 660,
      "energy": -1.0554061795057954,
      "backend": "high_esp"
    },
    {
      "iteration": 661,
      "energy": -1.0392074628007222,
      "backend": "high_esp"
    },
    {
      "iteration": 662,
      "energy": -1.0490248029412386,
      "backend": "high_esp"
    },
    {
      "iteration": 663,
      "energy": -1.0643876100789027,
      "backend": "high_esp"
    },
    {
      "iteration": 664,
      "energy": -1.0500980685199564,
      "backend": "high_esp"
    },
    {
      "iteration": 665,
      "energy": -1.0495400012616445,
      "backend": "high_esp"
    },
    {
      "iteration": 666,
      "energy": -1.0537595360772203,
      "backend": "high_esp"
    },
    {
      "iteration": 667,
      "energy": -1.0546805211300787,
      "backend": "high_esp"
    },
    {
      "iteration": 668,
      "energy": -1.0438193362781076,
      "backend": "high_esp"
    },
    {
      "iteration": 669,
      "energy": -1.0453516214283405,
      "backend": "high_esp"
    },
    {
      "iteration": 670,
      "energy": -1.0644650399693478,
      "backend": "high_esp"
    },
    {
      "iteration": 671,
      "energy": -1.0463120084987865,
      "backend": "high_esp"
    },
    {
      "iteration": 672,
      "energy": -1.051314203027481,
      "backend": "high_esp"
    },
    {
      "iteration": 673,
      "energy": -1.0471300469593388,
      "backend": "high_esp"
    },
    {
      "iteration": 674,
      "energy": -1.0537712880368686,
      "backend": "high_esp"
    },
    {
      "iteration": 675,
      "energy": -1.05506153886641,
      "backend": "high_esp"
    },
    {
      "iteration": 676,
      "energy": -1.0497184525307415,
      "backend": "high_esp"
    },
    {
      "iteration": 677,
      "energy": -1.0514305304192288,
      "backend": "high_esp"
    },
    {
      "iteration": 678,
      "energy": -1.039609647885048,
      "backend": "high_esp"
    },
    {
      "iteration": 679,
      "energy": -1.0465378726442012,
      "backend": "high_esp"
    },
    {
      "iteration": 680,
      "energy": -1.038092716055184,
      "backend": "high_esp"
    },
    {
      "iteration": 681,
      "energy": -1.0318189856590199,
      "backend": "high_esp"
    },
    {
      "iteration": 682,
      "energy": -1.0449965084177377,
      "backend": "high_esp"
    },
    {
      "iteration": 683,
      "energy": -1.0461359071401988,
      "backend": "high_esp"
    },
    {
      "iteration": 684,
      "energy": -1.0546532715009898,
      "backend": "high_esp"
    },
    {
      "iteration": 685,
      "energy": -1.0385015858434417,
      "backend": "high_esp"
    },
    {
      "iteration": 686,
      "energy": -1.0519921572147326,
      "backend": "high_esp"
    },
    {
      "iteration": 687,
      "energy": -1.0594405638485735,
      "backend": "high_esp"
    },
    {
      "iteration": 688,
      "energy": -1.0538003744691453,
      "backend": "high_esp"
    },
    {
      "iteration": 689,
      "energy": -1.052891077528491,
      "backend": "high_esp"
    },
    {
      "iteration": 690,
      "energy": -1.0384175098149484,
      "backend": "high_esp"
    },
    {
      "iteration": 691,
      "energy": -1.0434750152245085,
      "backend": "high_esp"
    },
    {
      "iteration": 692,
      "energy": -1.0259071686616423,
      "backend": "high_esp"
    },
    {
      "iteration": 693,
      "energy": -1.0288703526789007,
      "backend": "high_esp"
    },
    {
      "iteration": 694,
      "energy": -1.0613944359138685,
      "backend": "high_esp"
    },
    {
      "iteration": 695,
      "energy": -1.0446298639134062,
      "backend": "high_esp"
    },
    {
      "iteration": 696,
      "energy": -1.0591234429026946,
      "backend": "high_esp"
    },
    {
      "iteration": 697,
      "energy": -1.04677155605612,
      "backend": "high_esp"
    },
    {
      "iteration": 698,
      "energy": -1.0308332025857525,
      "backend": "high_esp"
    },
    {
      "iteration": 699,
      "energy": -1.054871040776041,
      "backend": "high_esp"
    },
    {
      "iteration": 700,
      "energy": -1.0553339693676798,
      "backend": "high_esp"
    },
    {
      "iteration": 701,
      "energy": -1.053400713342469,
      "backend": "high_esp"
    },
    {
      "iteration": 702,
      "energy": -1.054207398451225,
      "backend": "high_esp"
    },
    {
      "iteration": 703,
      "energy": -1.060700856430216,
      "backend": "high_esp"
    },
    {
      "iteration": 704,
      "energy": -1.0481098714168118,
      "backend": "high_esp"
    },
    {
      "iteration": 705,
      "energy": -1.0425680475852435,
      "backend": "high_esp"
    },
    {
      "iteration": 706,
      "energy": -1.041024107085447,
      "backend": "high_esp"
    },
    {
      "iteration": 707,
      "energy": -1.0383148298888691,
      "backend": "high_esp"
    },
    {
      "iteration": 708,
      "energy": -1.0507214891032823,
      "backend": "high_esp"
    },
    {
      "iteration": 709,
      "energy": -1.0442550328665385,
      "backend": "high_esp"
    },
    {
      "iteration": 710,
      "energy": -1.0472842585058444,
      "backend": "high_esp"
    },
    {
      "iteration": 711,
      "energy": -1.057076281167574,
      "backend": "high_esp"
    },
    {
      "iteration": 712,
      "energy": -1.036715445720583,
      "backend": "high_esp"
    },
    {
      "iteration": 713,
      "energy": -1.0586989567565546,
      "backend": "high_esp"
    },
    {
      "iteration": 714,
      "energy": -1.0464887549461213,
      "backend": "high_esp"
    },
    {
      "iteration": 715,
      "energy": -1.0485950915686788,
      "backend": "high_esp"
    },
    {
      "iteration": 716,
      "energy": -1.050308198179285,
      "backend": "high_esp"
    },
    {
      "iteration": 717,
      "energy": -1.0347332813174435,
      "backend": "high_esp"
    },
    {
      "iteration": 718,
      "energy": -1.0577295590930063,
      "backend": "high_esp"
    },
    {
      "iteration": 719,
      "energy": -1.06823215961272,
      "backend": "high_esp"
    },
    {
      "iteration": 720,
      "energy": -1.0494371874007111,
      "backend": "high_esp"
    },
    {
      "iteration": 721,
      "energy": -1.0408037997288746,
      "backend": "high_esp"
    },
    {
      "iteration": 722,
      "energy": -1.0566694210120309,
      "backend": "high_esp"
    },
    {
      "iteration": 723,
      "energy": -1.0526332866346804,
      "backend": "high_esp"
    },
    {
      "iteration": 724,
      "energy": -1.0557965794241253,
      "backend": "high_esp"
    },
    {
      "iteration": 725,
      "energy": -1.0421957471171042,
      "backend": "high_esp"
    },
    {
      "iteration": 726,
      "energy": -1.0436890431913415,
      "backend": "high_esp"
    },
    {
      "iteration": 727,
      "energy": -1.041149114116457,
      "backend": "high_esp"
    },
    {
      "iteration": 728,
      "energy": -1.0447964467445738,
      "backend": "high_esp"
    },
    {
      "iteration": 729,
      "energy": -1.0541210750196406,
      "backend": "high_esp"
    },
    {
      "iteration": 730,
      "energy": -1.0262795814826737,
      "backend": "high_esp"
    },
    {
      "iteration": 731,
      "energy": -1.0507442316539473,
      "backend": "high_esp"
    },
    {
      "iteration": 732,
      "energy": -1.0552578191503568,
      "backend": "high_esp"
    },
    {
      "iteration": 733,
      "energy": -1.0477461973585114,
      "backend": "high_esp"
    },
    {
      "iteration": 734,
      "energy": -1.0370044923556474,
      "backend": "high_esp"
    },
    {
      "iteration": 735,
      "energy": -1.061777783964713,
      "backend": "high_esp"
    },
    {
      "iteration": 736,
      "energy": -1.0449847062993853,
      "backend": "high_esp"
    },
    {
      "iteration": 737,
      "energy": -1.0474206889473536,
      "backend": "high_esp"
    },
    {
      "iteration": 738,
      "energy": -1.0424278876703021,
      "backend": "high_esp"
    },
    {
      "iteration": 739,
      "energy": -1.0465727172585049,
      "backend": "high_esp"
    },
    {
      "iteration": 740,
      "energy": -1.0450475883367594,
      "backend": "high_esp"
    },
    {
      "iteration": 741,
      "energy": -1.0314754658371144,
      "backend": "high_esp"
    },
    {
      "iteration": 742,
      "energy": -1.0327937275115315,
      "backend": "high_esp"
    },
    {
      "iteration": 743,
      "energy": -1.0448570482486377,
      "backend": "high_esp"
    },
    {
      "iteration": 744,
      "energy": -1.0506725956875702,
      "backend": "high_esp"
    },
    {
      "iteration": 745,
      "energy": -1.0476116506063142,
      "backend": "high_esp"
    },
    {
      "iteration": 746,
      "energy": -1.0403673590827756,
      "backend": "high_esp"
    },
    {
      "iteration": 747,
      "energy": -1.0418991636137749,
      "backend": "high_esp"
    },
    {
      "iteration": 748,
      "energy": -1.0617914940760405,
      "backend": "high_esp"
    },
    {
      "iteration": 749,
      "energy": -1.0447291428170993,
      "backend": "high_esp"
    },
    {
      "iteration": 750,
      "energy": -1.0548017675276549,
      "backend": "high_esp"
    },
    {
      "iteration": 751,
      "energy": -1.0537010548480532,
      "backend": "high_esp"
    },
    {
      "iteration": 752,
      "energy": -1.0381375274766496,
      "backend": "high_esp"
    },
    {
      "iteration": 753,
      "energy": -1.0553320726239865,
      "backend": "high_esp"
    },
    {
      "iteration": 754,
      "energy": -1.0409340967084113,
      "backend": "high_esp"
    },
    {
      "iteration": 755,
      "energy": -1.0395696683407893,
      "backend": "high_esp"
    },
    {
      "iteration": 756,
      "energy": -1.0502742008287198,
      "backend": "high_esp"
    },
    {
      "iteration": 757,
      "energy": -1.0464867909368685,
      "backend": "high_esp"
    },
    {
      "iteration": 758,
      "energy": -1.0539578279682174,
      "backend": "high_esp"
    },
    {
      "iteration": 759,
      "energy": -1.0471886521479918,
      "backend": "high_esp"
    },
    {
      "iteration": 760,
      "energy": -1.0471723586833375,
      "backend": "high_esp"
    },
    {
      "iteration": 761,
      "energy": -1.0599432702282976,
      "backend": "high_esp"
    },
    {
      "iteration": 762,
      "energy": -1.0470006620015837,
      "backend": "high_esp"
    },
    {
      "iteration": 763,
      "energy": -1.0561563367944915,
      "backend": "high_esp"
    },
    {
      "iteration": 764,
      "energy": -1.0638387163875276,
      "backend": "high_esp"
    },
    {
      "iteration": 765,
      "energy": -1.0507368420018202,
      "backend": "high_esp"
    },
    {
      "iteration": 766,
      "energy": -1.0476380789603033,
      "backend": "high_esp"
    },
    {
      "iteration": 767,
      "energy": -1.056513566458019,
      "backend": "high_esp"
    },
    {
      "iteration": 768,
      "energy": -1.063767734204938,
      "backend": "high_esp"
    },
    {
      "iteration": 769,
      "energy": -1.0506410486474744,
      "backend": "high_esp"
    },
    {
      "iteration": 770,
      "energy": -1.0407558181053025,
      "backend": "high_esp"
    },
    {
      "iteration": 771,
      "energy": -1.0332676848838045,
      "backend": "high_esp"
    },
    {
      "iteration": 772,
      "energy": -1.0378423324586292,
      "backend": "high_esp"
    },
    {
      "iteration": 773,
      "energy": -1.040290293086391,
      "backend": "high_esp"
    },
    {
      "iteration": 774,
      "energy": -1.0520671199988907,
      "backend": "high_esp"
    },
    {
      "iteration": 775,
      "energy": -1.0662151360935204,
      "backend": "high_esp"
    },
    {
      "iteration": 776,
      "energy": -1.0281401662332608,
      "backend": "high_esp"
    },
    {
      "iteration": 777,
      "energy": -1.0588787778815987,
      "backend": "high_esp"
    },
    {
      "iteration": 778,
      "energy": -1.0570430025141015,
      "backend": "high_esp"
    },
    {
      "iteration": 779,
      "energy": -1.0382041376127547,
      "backend": "high_esp"
    },
    {
      "iteration": 780,
      "energy": -1.0421300674264462,
      "backend": "high_esp"
    },
    {
      "iteration": 781,
      "energy": -1.0580382943564024,
      "backend": "high_esp"
    },
    {
      "iteration": 782,
      "energy": -1.0434245249415568,
      "backend": "high_esp"
    },
    {
      "iteration": 783,
      "energy": -1.0435078831544102,
      "backend": "high_esp"
    },
    {
      "iteration": 784,
      "energy": -1.0464405892829303,
      "backend": "high_esp"
    },
    {
      "iteration": 785,
      "energy": -1.0406666602217063,
      "backend": "high_esp"
    },
    {
      "iteration": 786,
      "energy": -1.0369745112806932,
      "backend": "high_esp"
    },
    {
      "iteration": 787,
      "energy": -1.0605005069850133,
      "backend": "high_esp"
    },
    {
      "iteration": 788,
      "energy": -1.022301075913412,
      "backend": "high_esp"
    },
    {
      "iteration": 789,
      "energy": -1.05676597345164,
      "backend": "high_esp"
    },
    {
      "iteration": 790,
      "energy": -1.0481943761037218,
      "backend": "high_esp"
    },
    {
      "iteration": 791,
      "energy": -1.0587998431869028,
      "backend": "high_esp"
    },
    {
      "iteration": 792,
      "energy": -1.0520523188708453,
      "backend": "high_esp"
    },
    {
      "iteration": 793,
      "energy": -1.0587769693082576,
      "backend": "high_esp"
    },
    {
      "iteration": 794,
      "energy": -1.0399430674026455,
      "backend": "high_esp"
    },
    {
      "iteration": 795,
      "energy": -1.047369938075739,
      "backend": "high_esp"
    },
    {
      "iteration": 796,
      "energy": -1.0629833270451985,
      "backend": "high_esp"
    },
    {
      "iteration": 797,
      "energy": -1.0339788457998371,
      "backend": "high_esp"
    },
    {
      "iteration": 798,
      "energy": -1.0581182653305197,
      "backend": "high_esp"
    },
    {
      "iteration": 799,
      "energy": -1.0528988835021846,
      "backend": "high_esp"
    },
    {
      "iteration": 800,
      "energy": -1.0674160836478437,
      "backend": "high_esp"
    },
    {
      "iteration": 801,
      "energy": -1.046663206427665,
      "backend": "high_esp"
    },
    {
      "iteration": 802,
      "energy": -1.0666719212160016,
      "backend": "high_esp"
    },
    {
      "iteration": 803,
      "energy": -1.0494243927572307,
      "backend": "high_esp"
    },
    {
      "iteration": 804,
      "energy": -1.0440096932805913,
      "backend": "high_esp"
    },
    {
      "iteration": 805,
      "energy": -1.0590263261482156,
      "backend": "high_esp"
    },
    {
      "iteration": 806,
      "energy": -1.0477894451402332,
      "backend": "high_esp"
    },
    {
      "iteration": 807,
      "energy": -1.050644291082186,
      "backend": "high_esp"
    },
    {
      "iteration": 808,
      "energy": -1.032162152133899,
      "backend": "high_esp"
    },
    {
      "iteration": 809,
      "energy": -1.0532346746547088,
      "backend": "high_esp"
    },
    {
      "iteration": 810,
      "energy": -1.0417368054915142,
      "backend": "high_esp"
    },
    {
      "iteration": 811,
      "energy": -1.051342111470747,
      "backend": "high_esp"
    },
    {
      "iteration": 812,
      "energy": -1.025221838843512,
      "backend": "high_esp"
    },
    {
      "iteration": 813,
      "energy": -1.0496258430112415,
      "backend": "high_esp"
    },
    {
      "iteration": 814,
      "energy": -1.0617655470511338,
      "backend": "high_esp"
    },
    {
      "iteration": 815,
      "energy": -1.0495384025417551,
      "backend": "high_esp"
    }
  ],
  "esp_data": {
    "low_esp": 0.7972010756418796,
    "high_esp": 0.8983701194209472
  }
}